mu_repo/__docs__.py
mu_repo/__init__.py
mu_repo/__references__.py
mu_repo/_color_console.py
mu_repo/action_add_commit_push.py
mu_repo/action_auto_update.py
mu_repo/action_checkout.py
mu_repo/action_clone.py
mu_repo/action_default.py
mu_repo/action_diff.py
mu_repo/action_find_branch.py
mu_repo/action_fix_eol.py
mu_repo/action_get_vars.py
mu_repo/action_group.py
mu_repo/action_install.py
mu_repo/action_list.py
mu_repo/action_open_url.py
mu_repo/action_rebase.py
mu_repo/action_register.py
mu_repo/action_set_var.py
mu_repo/action_st.py
mu_repo/action_sync.py
mu_repo/action_unregister.py
mu_repo/action_up.py
mu_repo/backwards.py
mu_repo/backwards_stringio.py
mu_repo/config.py
mu_repo/execute_command.py
mu_repo/execute_git_command_in_thread.py
mu_repo/execute_parallel_command.py
mu_repo/get_repos_and_curr_branch.py
mu_repo/get_repos_and_local_branches.py
mu_repo/keep_files_synched.py
mu_repo/null.py
mu_repo/print_.py
mu_repo/repos_with_changes.py
mu_repo/rmtree.py
mu_repo/system_mutex.py
mu_repo/thread_pool.py
mu_repo/umsgpack_s.py
mu_repo/umsgpack_s_conn.py
mu_repo-1.9.0.dist-info/LICENSE
mu_repo-1.9.0.dist-info/METADATA
mu_repo-1.9.0.dist-info/WHEEL
mu_repo-1.9.0.dist-info/entry_points.txt
mu_repo-1.9.0.dist-info/top_level.txt
mu_repo-1.9.0.dist-info/RECORD
