Metadata-Version: 2.1
Name: mu-repo
Version: 1.9.0
Summary: Tool to work with multiple git repositories
Home-page: http://fabioz.github.io/mu-repo
Author: Fabio Zadrozny
Classifier: Development Status :: 6 - Mature
Classifier: Environment :: Console
Classifier: Intended Audience :: Developers
Classifier: License :: OSI Approved :: GNU General Public License v3 (GPLv3)
Classifier: Operating System :: OS Independent
Classifier: Programming Language :: Python
Classifier: Topic :: Software Development :: Version Control
License-File: LICENSE
